modemscraper/__init__.py
modemscraper/modemscraper.py
modemscraper/parser.py
modemscraper-0.2.0.dist-info/DESCRIPTION.rst
modemscraper-0.2.0.dist-info/METADATA
modemscraper-0.2.0.dist-info/RECORD
modemscraper-0.2.0.dist-info/WHEEL
modemscraper-0.2.0.dist-info/metadata.json
modemscraper-0.2.0.dist-info/top_level.txt
