Metadata-Version: 2.0
Name: modemscraper
Version: 0.2.0
Summary: Modem scraper retrieves important information from Surfboard-like modem status pages.
Home-page: https://github.com/nightexcessive/modemscraper
Author: Michael Johnson
Author-email: michael@johnson.computer
License: GNU General Public License v3
Keywords: modemscraper
Platform: UNKNOWN
Classifier: Development Status :: 2 - Pre-Alpha
Classifier: Intended Audience :: Developers
Classifier: License :: OSI Approved :: GNU General Public License v3 (GPLv3)
Classifier: Natural Language :: English
Classifier: Programming Language :: Python :: 2
Classifier: Programming Language :: Python :: 2.6
Classifier: Programming Language :: Python :: 2.7
Classifier: Programming Language :: Python :: 3
Classifier: Programming Language :: Python :: 3.3
Classifier: Programming Language :: Python :: 3.4
Classifier: Programming Language :: Python :: 3.5
Requires-Dist: Pint
Requires-Dist: beautifulsoup4
Requires-Dist: requests
